{
  "indexe": [
    {
      "collectionGroup": "ill",
      "queryScope": "COLLECTION",
      "fields": [
        {
          "fieldPath": "creators_full",
          "arrayConfig": "CONTAINS"
        },
        {
          "fieldPath": "position",
          "order": "ASCENDING"
        }
      ]
    },
    {
      "collectionGroup": "ill",
      "queryScope": "COLLECTION",
      "fields": [
        {
          "fieldPath": "gd_version",
          "order": "ASCENDING"
        },
        {
          "fieldPath": "position",
          "order": "ASCENDING"
        }
      ]
    },
    {
      "collectionGroup": "ill",
      "queryScope": "COLLECTION",
      "fields": [
        {
          "fieldPath": "level_id",
          "order": "ASCENDING"
        },
        {
          "fieldPath": "position",
          "order": "ASCENDING"
        }
      ]
    },
    {
      "collectionGroup": "ill",
      "queryScope": "COLLECTION",
      "fields": [
        {
          "fieldPath": "name",
          "order": "ASCENDING"
        },
        {
          "fieldPath": "position",
          "order": "ASCENDING"
        }
      ]
    },
    {
      "collectionGroup": "ill",
      "queryScope": "COLLECTION",
      "fields": [
        {
          "fieldPath": "tags",
          "arrayConfig": "CONTAINS"
        },
        {
          "fieldPath": "position",
          "order": "ASCENDING"
        }
      ]
    }
  ],
  "fieldOverrides": []
}
